{
  "mainBigImage": {

    "subjects": [
      {
        "name": "Developmental Biology and Stem Cells",
        "path": "#"
      },
      {
        "name": "Neuroscience",
        "path": "#"
      }
    ],
    "title": "Retrograde fibroblast growth factor 22 (FGF22) signaling regulates insulin-like growth factor 2 (IGF2) expression for activity-dependent synapse stabilization in the mammalian brain",
    "firstAuthor": "Akiko Terauchi",
    "multipleAuthors": true,
    "link": "#",
    "content": "Feedback signaling between the synapse and nucleus via FGF22 and IGF2 directs the activity-dependent stabilization of presynaptic terminals in the mouse hippocampus.",
    "category": {
      "name": "Research article",
      "path": "#"
    },
    "date": {
      "forHuman": "May 16, 2016",
      "forMachine": "20160516"
    },
    "hasBigImage": "true",
    "image": {
      "defaultPath": "http://unsplash.it/250/140/",
      "srcset": "http://unsplash.it/500/280/ 500w, http://unsplash.it/250/140/ 250w"
    }
  },

  "mainSmallImage": {

    "subjects": [
      {
        "name": "Developmental Biology and Stem Cells",
        "path": "#"
      },
      {
        "name": "Neuroscience",
        "path": "#"
      }
    ],
    "title": "Retrograde fibroblast growth factor 22 (FGF22) signaling regulates insulin-like growth factor 2 (IGF2) expression for activity-dependent synapse stabilization in the mammalian brain",
    "firstAuthor": "Akiko Terauchi",
    "link": "#",
    "multipleAuthors": true,
    "content": "Feedback signaling between the synapse and nucleus via FGF22 and IGF2 directs the activity-dependent stabilization of presynaptic terminals in the mouse hippocampus.",
    "category": {
      "name": "Research article",
      "path": "#"
    },
    "date": {
      "forHuman": "May 16, 2016",
      "forMachine": "20160516"
    },
    "hasSmallImage": "true",
    "image": {
      "defaultPath": "http://unsplash.it/250/140/",
      "srcset": "http://unsplash.it/140/140/ 140w, http://unsplash.it/70/70/ 70w"
    }
  },

  "mainNoImage": {

    "subjects": [
      {
        "name": "Developmental Biology and Stem Cells",
        "path": "#"
      },
      {
        "name": "Neuroscience",
        "path": "#"
      }
    ],
    "title": "Retrograde fibroblast growth factor 22 (FGF22) signaling regulates insulin-like growth factor 2 (IGF2) expression for activity-dependent synapse stabilization in the mammalian brain",
    "firstAuthor": "Akiko Terauchi",
    "link": "#",
    "multipleAuthors": true,
    "content": "Feedback signaling between the synapse and nucleus via FGF22 and IGF2 directs the activity-dependent stabilization of presynaptic terminals in the mouse hippocampus.",
    "category": {
      "name": "Research article",
      "path": "#"
    },
    "date": {
      "forHuman": "May 16, 2016",
      "forMachine": "20160516"
    }

  },

  "secondaryBigImage": {
    "subjects": [
      {
        "name": "Biochemistry",
        "path": "#"
      },
      {
        "name": "Neuroscience",
        "path": "#"
      }
    ],
    "title": "Mapping Ebola in wild animals for better disease control",
    "firstAuthor": "Bloggs, J.",
    "multipleAuthors": true,
    "link": "#",
    "category": {
      "name": "Insight",
      "path": "#"
    },
    "date": {
      "forHuman": "Dec 16, 2015",
      "forMachine": "2015-12-16"
    },
    "hasBigImage": "true",
    "image": {
      "defaultPath": "http://unsplash.it/250/140/",
      "srcset": "http://unsplash.it/500/280/ 500w, http://unsplash.it/250/140/ 250w"
    }
  },

  "secondarySmallImage": {
    "subjects": [
      {
        "name": "Biochemistry",
        "path": "#"
      },
      {
        "name": "Neuroscience",
        "path": "#"
      }
    ],
    "title": "Mapping Ebola in wild animals for better disease control",
    "link": "#",
    "firstAuthor": "Bloggs, J.",
    "multipleAuthors": true,
    "category": {
      "name": "Insight",
      "path": "#"
    },
    "date": {
      "forHuman": "Dec 16, 2015",
      "forMachine": "2015-12-16"
    },
    "hasSmallImage": "true",
    "image": {
      "defaultPath": "http://unsplash.it/250/140/",
      "srcset": "http://unsplash.it/140/140/ 140w, http://unsplash.it/70/70/ 70w"
    }
  },

  "secondaryNoImage": {
    "subjects": [
      {
        "name": "Biochemistry",
        "path": "#"
      },
      {
        "name": "Neuroscience",
        "path": "#"
      }
    ],
    "title": "Mapping Ebola in wild animals for better disease control",
    "link": "#",
    "firstAuthor": "Bloggs, J.",
    "multipleAuthors": true,
    "category": {
      "name": "Insight",
      "path": "#"
    },
    "date": {
      "forHuman": "Dec 16, 2015",
      "forMachine": "2015-12-16"
    }
  },

  "event": {
    "link": "#",
    "title": "HSFP Postdoctoral Fellowships from the Human Frontier Science Program",
    "subheading": "eLife",
    "date": {
      "isExpanded": true,
      "forHuman": {
        "dayOfMonth": "18",
        "month": "Dec",
        "year": "2015"
      },
      "forMachine": "2015-12-16"
    }
  },

  "article": {
    "meta": "Built upon by",
    "title": "Stem cells and  fluid flow drive cyst formation in an invertebrate excretory organ",
    "firstAuthor": "H Thi-Kim Vu",
    "link": "#",
    "multipleAuthors": true,
    "category": {
      "name": "Research advance",
      "path": "#"
    },
    "date": {
      "forHuman": "Dec 16, 2015",
      "forMachine": "2015-05-12"
    }
  },

  "year": 2016,
  "assetsPath": "../../assets"

}
