{
  "hero-banner": {
    "item": {
      "image": {
        "fallback": {
          "defaultPath": "https://unsplash.it/1114/336",
          "altText": ""
        }
      },
      "subjects": {
        "list": [
          {
            "name": "Structure Biology and Mulecular Biophysics",
            "url": "#"
          }
        ]
      },
      "title": "Filamentation and the regulation of PRPP synthase",
      "summary": "Cryo-EM structures of two types of prokaryotic Phosphoribosyl pyrophosphate synthase filaments reveal tat filamentation into cytoophidia provides a new layer of metabolic regulation.",
      "authors": [
        {
          "list": [
            {
              "name": "Lee R Berger",
              "url": "#"
            },
            {
              "name": "John Hawks",
              "url": "#"
            }
          ]
        }
      ],
      "meta": {
        "url": "#",
        "text": "Research article",
        "date": {
          "forHuman": {
            "dayOfMonth": 23,
            "month": "Jan",
            "year": 2022
          },
          "forMachine": "2022-01-23"
        }
      }
    }
  }
}