{
  "title": "Oldest <i>Homo</i> and Pliocene biogeography of the Malawi rift",
  "origin": "Nature 365:833–836. PMID 8413666",
  "hasAuthors": true,
  "authorLists": [
    {
      "authors": [
        {
          "name": "Schrenk F",
          "url": "https://scholar.google.com/scholar?q=%22author:Schrenk%20F%22"
        },
        {
          "name": "Bromage TG",
          "url": false
        },
        {
          "name": "Betzler CG",
          "url": false
        },
        {
          "name": "Ring U",
          "url": false
        },
        {
          "name": "Juwayeyi YM",
          "url": false
        }
      ],
      "suffix": "(1993)"
    }
  ],
  "doi": {
    "doi": "10.1038/365833a0"
  },
  "hasAbstracts": false
}
